five.formlib-3.0-py3.11-nspkg.pth
five/formlib/__init__.py
five/formlib/add.pt
five/formlib/configure.zcml
five/formlib/edit.pt
five/formlib/formbase.py
five/formlib/macros.py
five/formlib/meta.zcml
five/formlib/metaconfigure.py
five/formlib/objectwidget.pt
five/formlib/objectwidget.py
five/formlib/tests/__init__.py
five/formlib/tests/configure.zcml
five/formlib/tests/content.py
five/formlib/tests/formlib.txt
five/formlib/tests/forms.txt
five/formlib/tests/schemacontent.py
five/formlib/tests/test_formlib.py
five/formlib/tests/view.py
five/formlib/tests/locales/formtest.pot
five/formlib/tests/locales/de/LC_MESSAGES/formtest.po
five.formlib-3.0.dist-info/LICENSE.txt
five.formlib-3.0.dist-info/METADATA
five.formlib-3.0.dist-info/WHEEL
five.formlib-3.0.dist-info/namespace_packages.txt
five.formlib-3.0.dist-info/top_level.txt
five.formlib-3.0.dist-info/RECORD
