Metadata-Version: 2.1
Name: five.formlib
Version: 3.0
Summary: zope.formlib integration for Zope.
Home-page: https://github.com/zopefoundation/five.formlib
Author: Zope Foundation
Author-email: zope-dev@zope.dev
License: ZPL 2.1
Keywords: zope zope5 five formlib
Classifier: Development Status :: 6 - Mature
Classifier: Environment :: Web Environment
Classifier: Framework :: Zope :: 5
Classifier: Intended Audience :: Developers
Classifier: License :: OSI Approved :: Zope Public License
Classifier: Operating System :: OS Independent
Classifier: Programming Language :: Python :: 3
Classifier: Programming Language :: Python :: 3.7
Classifier: Programming Language :: Python :: 3.8
Classifier: Programming Language :: Python :: 3.9
Classifier: Programming Language :: Python :: 3.10
Classifier: Programming Language :: Python :: 3.11
Classifier: Programming Language :: Python :: Implementation :: CPython
Classifier: Topic :: Internet :: WWW/HTTP :: Dynamic Content
Classifier: Topic :: Internet :: WWW/HTTP :: WSGI :: Application
Classifier: Topic :: Software Development :: Libraries :: Application Frameworks
License-File: LICENSE.txt
Requires-Dist: setuptools
Requires-Dist: transaction
Requires-Dist: zope.app.form
Requires-Dist: zope.browser
Requires-Dist: zope.browsermenu
Requires-Dist: zope.component
Requires-Dist: zope.event
Requires-Dist: zope.formlib (>=4.4)
Requires-Dist: zope.i18nmessageid
Requires-Dist: zope.interface
Requires-Dist: zope.lifecycleevent
Requires-Dist: zope.location
Requires-Dist: zope.publisher
Requires-Dist: zope.schema
Requires-Dist: ExtensionClass
Requires-Dist: Zope (>=4)
